dolphin_mcp/__init__.py
dolphin_mcp/cli.py
dolphin_mcp/client.py
dolphin_mcp/utils.py
dolphin_mcp/providers/__init__.py
dolphin_mcp/providers/anthropic.py
dolphin_mcp/providers/lmstudio.py
dolphin_mcp/providers/ollama.py
dolphin_mcp/providers/openai.py
dolphin_mcp-0.1.3.dist-info/METADATA
dolphin_mcp-0.1.3.dist-info/WHEEL
dolphin_mcp-0.1.3.dist-info/entry_points.txt
dolphin_mcp-0.1.3.dist-info/top_level.txt
dolphin_mcp-0.1.3.dist-info/RECORD
