Metadata-Version: 2.4
Name: dolphin-mcp
Version: 0.1.3
Summary: A flexible Python client for interacting with Model Context Protocol (MCP) servers
Author: Dolphin MCP Team
License: MIT
Classifier: Programming Language :: Python :: 3
Classifier: License :: OSI Approved :: MIT License
Classifier: Operating System :: OS Independent
Requires-Python: >=3.8
Requires-Dist: openai
Requires-Dist: mcp[cli]
Requires-Dist: python-dotenv
Requires-Dist: anthropic
Requires-Dist: ollama
Requires-Dist: jsonschema
Provides-Extra: dev
Requires-Dist: pytest; extra == "dev"
Requires-Dist: pytest-asyncio; extra == "dev"
Requires-Dist: pytest-mock; extra == "dev"
Requires-Dist: uv; extra == "dev"
Provides-Extra: demo
Requires-Dist: mcp-server-sqlite; extra == "demo"
